readydata/__init__.py
readydata/adapters.py
readydata/client.py
readydata/models.py
readydata/validation.py
readydata_sdk_py-0.1.7.dist-info/METADATA
readydata_sdk_py-0.1.7.dist-info/WHEEL
readydata_sdk_py-0.1.7.dist-info/RECORD
